levellogger/__init__.py
levellogger/logger.py
simplelogger/__init__.py
simplelogger/logger.py
levellogger-0.2.5.dist-info/LICENSE
levellogger-0.2.5.dist-info/METADATA
levellogger-0.2.5.dist-info/WHEEL
levellogger-0.2.5.dist-info/top_level.txt
levellogger-0.2.5.dist-info/RECORD
