Metadata-Version: 2.1
Name: levellogger
Version: 0.2.5
License-File: LICENSE
Requires-Dist: datetime
Requires-Dist: typing
